kupka/__init__.py
kupka/py.typed
kupka/_impl/__init__.py
kupka/_impl/cache.py
kupka/_impl/graph_tools.py
kupka/_impl/kupka.py
kupka/_impl/kupklass.py
kupka/_impl/nodes.py
kupka/_impl/settings.py
kupka/_impl/visualisation.py
kupka/_impl/wrappers.py
kupka/_impl/execution/__init__.py
kupka/_impl/execution/core.py
kupka/_impl/execution/multiprocessing.py
kupka/_impl/execution/sequential.py
kupka-0.0.2.dist-info/licenses/LICENSE
kupka-0.0.2.dist-info/METADATA
kupka-0.0.2.dist-info/WHEEL
kupka-0.0.2.dist-info/top_level.txt
kupka-0.0.2.dist-info/RECORD
