Metadata-Version: 2.4
Name: kupka
Version: 0.0.2
Summary: A Flexible Computational Graph Library For Python
Author: Norvan Sahiner
Maintainer: Norvan Sahiner
License:                                  Apache License
Project-URL: homepage, https://github.com/norvan/kupka
Project-URL: documentation, https://github.com/norvan/kupka
Project-URL: source, https://github.com/norvan/kupka
Project-URL: download, https://pypi.org/project/kupka/#files
Project-URL: tracker, https://github.com/norvan/kupka/issues
Classifier: Intended Audience :: Developers
Classifier: Intended Audience :: Science/Research
Classifier: Programming Language :: Python
Classifier: Programming Language :: Python :: 3
Classifier: Programming Language :: Python :: 3.10
Classifier: Programming Language :: Python :: 3.11
Classifier: Programming Language :: Python :: 3.12
Classifier: Programming Language :: Python :: 3.13
Classifier: Programming Language :: Python :: 3 :: Only
Classifier: Topic :: Software Development
Classifier: Topic :: Scientific/Engineering
Classifier: Typing :: Typed
Classifier: Operating System :: Microsoft :: Windows
Classifier: Operating System :: POSIX
Classifier: Operating System :: Unix
Classifier: Operating System :: MacOS
Requires-Python: >=3.10
License-File: LICENSE
Requires-Dist: pydot
Provides-Extra: viz
Requires-Dist: pydot; extra == "viz"
Provides-Extra: dev
Requires-Dist: build; extra == "dev"
Requires-Dist: twine; extra == "dev"
Requires-Dist: tox; extra == "dev"
Requires-Dist: mypy; extra == "dev"
Requires-Dist: pytest; extra == "dev"
Requires-Dist: mock; extra == "dev"
Requires-Dist: ruff; extra == "dev"
Requires-Dist: black; extra == "dev"
Requires-Dist: isort; extra == "dev"
Dynamic: license-file
